examples/__init__.py
examples/example.py
pyebooks/__init__.py
pyebooks/helpers.py
pyebooks/pyebooks.py
pyebooks-0.1.0.dist-info/DESCRIPTION.rst
pyebooks-0.1.0.dist-info/METADATA
pyebooks-0.1.0.dist-info/RECORD
pyebooks-0.1.0.dist-info/WHEEL
pyebooks-0.1.0.dist-info/metadata.json
pyebooks-0.1.0.dist-info/top_level.txt
